{"nodes": [{"id": "useorgadmin", "label": "useOrgAdmin.ts", "file_type": "code", "source_file": "src\\hooks\\useOrgAdmin.ts", "source_location": "L1"}, {"id": "useorgadmin_useorgadminmembers", "label": "useOrgAdminMembers()", "file_type": "code", "source_file": "src\\hooks\\useOrgAdmin.ts", "source_location": "L15"}, {"id": "useorgadmin_useorgadmindashboardmembers", "label": "useOrgAdminDashboardMembers()", "file_type": "code", "source_file": "src\\hooks\\useOrgAdmin.ts", "source_location": "L21"}, {"id": "useorgadmin_useinvitemember", "label": "useInviteMember()", "file_type": "code", "source_file": "src\\hooks\\useOrgAdmin.ts", "source_location": "L27"}, {"id": "useorgadmin_usebulkimportmembers", "label": "useBulkImportMembers()", "file_type": "code", "source_file": "src\\hooks\\useOrgAdmin.ts", "source_location": "L36"}, {"id": "useorgadmin_useorgsettings", "label": "useOrgSettings()", "file_type": "code", "source_file": "src\\hooks\\useOrgAdmin.ts", "source_location": "L44"}, {"id": "useorgadmin_useorgbillingusage", "label": "useOrgBillingUsage()", "file_type": "code", "source_file": "src\\hooks\\useOrgAdmin.ts", "source_location": "L50"}, {"id": "useorgadmin_useorgactivity", "label": "useOrgActivity()", "file_type": "code", "source_file": "src\\hooks\\useOrgAdmin.ts", "source_location": "L56"}, {"id": "useorgadmin_useorgcourses", "label": "useOrgCourses()", "file_type": "code", "source_file": "src\\hooks\\useOrgAdmin.ts", "source_location": "L62"}, {"id": "useorgadmin_useorgenrollments", "label": "useOrgEnrollments()", "file_type": "code", "source_file": "src\\hooks\\useOrgAdmin.ts", "source_location": "L68"}, {"id": "useorgadmin_useorgcertificates", "label": "useOrgCertificates()", "file_type": "code", "source_file": "src\\hooks\\useOrgAdmin.ts", "source_location": "L74"}, {"id": "useorgadmin_useorgnotifications", "label": "useOrgNotifications()", "file_type": "code", "source_file": "src\\hooks\\useOrgAdmin.ts", "source_location": "L80"}, {"id": "useorgadmin_usemarkallnotificationsread", "label": "useMarkAllNotificationsRead()", "file_type": "code", "source_file": "src\\hooks\\useOrgAdmin.ts", "source_location": "L86"}, {"id": "useorgadmin_useupdateorgsettings", "label": "useUpdateOrgSettings()", "file_type": "code", "source_file": "src\\hooks\\useOrgAdmin.ts", "source_location": "L94"}, {"id": "useorgadmin_useorgsessionprogress", "label": "useOrgSessionProgress()", "file_type": "code", "source_file": "src\\hooks\\useOrgAdmin.ts", "source_location": "L102"}, {"id": "useorgadmin_useenrollmember", "label": "useEnrollMember()", "file_type": "code", "source_file": "src\\hooks\\useOrgAdmin.ts", "source_location": "L108"}, {"id": "useorgadmin_usebulkenrollmembers", "label": "useBulkEnrollMembers()", "file_type": "code", "source_file": "src\\hooks\\useOrgAdmin.ts", "source_location": "L116"}, {"id": "useorgadmin_useorgreporttypes", "label": "useOrgReportTypes()", "file_type": "code", "source_file": "src\\hooks\\useOrgAdmin.ts", "source_location": "L135"}, {"id": "useorgadmin_useorgreports", "label": "useOrgReports()", "file_type": "code", "source_file": "src\\hooks\\useOrgAdmin.ts", "source_location": "L141"}], "edges": [{"source": "useorgadmin", "target": "react_query", "relation": "imports_from", "confidence": "EXTRACTED", "source_file": "src\\hooks\\useOrgAdmin.ts", "source_location": "L1", "weight": 1.0}, {"source": "useorgadmin", "target": "organization_services", "relation": "imports_from", "confidence": "EXTRACTED", "source_file": "src\\hooks\\useOrgAdmin.ts", "source_location": "L2", "weight": 1.0}, {"source": "useorgadmin", "target": "catalogue_services", "relation": "imports_from", "confidence": "EXTRACTED", "source_file": "src\\hooks\\useOrgAdmin.ts", "source_location": "L3", "weight": 1.0}, {"source": "useorgadmin", "target": "learning_services", "relation": "imports_from", "confidence": "EXTRACTED", "source_file": "src\\hooks\\useOrgAdmin.ts", "source_location": "L4", "weight": 1.0}, {"source": "useorgadmin", "target": "notifications_services", "relation": "imports_from", "confidence": "EXTRACTED", "source_file": "src\\hooks\\useOrgAdmin.ts", "source_location": "L5", "weight": 1.0}, {"source": "useorgadmin", "target": "reports_services", "relation": "imports_from", "confidence": "EXTRACTED", "source_file": "src\\hooks\\useOrgAdmin.ts", "source_location": "L6", "weight": 1.0}, {"source": "useorgadmin", "target": "auth_services", "relation": "imports_from", "confidence": "EXTRACTED", "source_file": "src\\hooks\\useOrgAdmin.ts", "source_location": "L7", "weight": 1.0}, {"source": "useorgadmin", "target": "types", "relation": "imports_from", "confidence": "EXTRACTED", "source_file": "src\\hooks\\useOrgAdmin.ts", "source_location": "L8", "weight": 1.0}, {"source": "useorgadmin", "target": "organization_services", "relation": "imports_from", "confidence": "EXTRACTED", "source_file": "src\\hooks\\useOrgAdmin.ts", "source_location": "L9", "weight": 1.0}, {"source": "useorgadmin", "target": "catalogue_services", "relation": "imports_from", "confidence": "EXTRACTED", "source_file": "src\\hooks\\useOrgAdmin.ts", "source_location": "L10", "weight": 1.0}, {"source": "useorgadmin", "target": "learning_services", "relation": "imports_from", "confidence": "EXTRACTED", "source_file": "src\\hooks\\useOrgAdmin.ts", "source_location": "L11", "weight": 1.0}, {"source": "useorgadmin", "target": "types", "relation": "imports_from", "confidence": "EXTRACTED", "source_file": "src\\hooks\\useOrgAdmin.ts", "source_location": "L12", "weight": 1.0}, {"source": "useorgadmin", "target": "querykeys", "relation": "imports_from", "confidence": "EXTRACTED", "source_file": "src\\hooks\\useOrgAdmin.ts", "source_location": "L13", "weight": 1.0}, {"source": "useorgadmin", "target": "useorgadmin_useorgadminmembers", "relation": "contains", "confidence": "EXTRACTED", "source_file": "src\\hooks\\useOrgAdmin.ts", "source_location": "L15", "weight": 1.0}, {"source": "useorgadmin", "target": "useorgadmin_useorgadmindashboardmembers", "relation": "contains", "confidence": "EXTRACTED", "source_file": "src\\hooks\\useOrgAdmin.ts", "source_location": "L21", "weight": 1.0}, {"source": "useorgadmin", "target": "useorgadmin_useinvitemember", "relation": "contains", "confidence": "EXTRACTED", "source_file": "src\\hooks\\useOrgAdmin.ts", "source_location": "L27", "weight": 1.0}, {"source": "useorgadmin", "target": "useorgadmin_usebulkimportmembers", "relation": "contains", "confidence": "EXTRACTED", "source_file": "src\\hooks\\useOrgAdmin.ts", "source_location": "L36", "weight": 1.0}, {"source": "useorgadmin", "target": "useorgadmin_useorgsettings", "relation": "contains", "confidence": "EXTRACTED", "source_file": "src\\hooks\\useOrgAdmin.ts", "source_location": "L44", "weight": 1.0}, {"source": "useorgadmin", "target": "useorgadmin_useorgbillingusage", "relation": "contains", "confidence": "EXTRACTED", "source_file": "src\\hooks\\useOrgAdmin.ts", "source_location": "L50", "weight": 1.0}, {"source": "useorgadmin", "target": "useorgadmin_useorgactivity", "relation": "contains", "confidence": "EXTRACTED", "source_file": "src\\hooks\\useOrgAdmin.ts", "source_location": "L56", "weight": 1.0}, {"source": "useorgadmin", "target": "useorgadmin_useorgcourses", "relation": "contains", "confidence": "EXTRACTED", "source_file": "src\\hooks\\useOrgAdmin.ts", "source_location": "L62", "weight": 1.0}, {"source": "useorgadmin", "target": "useorgadmin_useorgenrollments", "relation": "contains", "confidence": "EXTRACTED", "source_file": "src\\hooks\\useOrgAdmin.ts", "source_location": "L68", "weight": 1.0}, {"source": "useorgadmin", "target": "useorgadmin_useorgcertificates", "relation": "contains", "confidence": "EXTRACTED", "source_file": "src\\hooks\\useOrgAdmin.ts", "source_location": "L74", "weight": 1.0}, {"source": "useorgadmin", "target": "useorgadmin_useorgnotifications", "relation": "contains", "confidence": "EXTRACTED", "source_file": "src\\hooks\\useOrgAdmin.ts", "source_location": "L80", "weight": 1.0}, {"source": "useorgadmin", "target": "useorgadmin_usemarkallnotificationsread", "relation": "contains", "confidence": "EXTRACTED", "source_file": "src\\hooks\\useOrgAdmin.ts", "source_location": "L86", "weight": 1.0}, {"source": "useorgadmin", "target": "useorgadmin_useupdateorgsettings", "relation": "contains", "confidence": "EXTRACTED", "source_file": "src\\hooks\\useOrgAdmin.ts", "source_location": "L94", "weight": 1.0}, {"source": "useorgadmin", "target": "useorgadmin_useorgsessionprogress", "relation": "contains", "confidence": "EXTRACTED", "source_file": "src\\hooks\\useOrgAdmin.ts", "source_location": "L102", "weight": 1.0}, {"source": "useorgadmin", "target": "useorgadmin_useenrollmember", "relation": "contains", "confidence": "EXTRACTED", "source_file": "src\\hooks\\useOrgAdmin.ts", "source_location": "L108", "weight": 1.0}, {"source": "useorgadmin", "target": "useorgadmin_usebulkenrollmembers", "relation": "contains", "confidence": "EXTRACTED", "source_file": "src\\hooks\\useOrgAdmin.ts", "source_location": "L116", "weight": 1.0}, {"source": "useorgadmin", "target": "useorgadmin_useorgreporttypes", "relation": "contains", "confidence": "EXTRACTED", "source_file": "src\\hooks\\useOrgAdmin.ts", "source_location": "L135", "weight": 1.0}, {"source": "useorgadmin", "target": "useorgadmin_useorgreports", "relation": "contains", "confidence": "EXTRACTED", "source_file": "src\\hooks\\useOrgAdmin.ts", "source_location": "L141", "weight": 1.0}]}