{"nodes": [{"id": "subscriptionmanagementpage", "label": "SubscriptionManagementPage.tsx", "file_type": "code", "source_file": "src\\pages\\learner\\SubscriptionManagementPage.tsx", "source_location": "L1"}, {"id": "subscriptionmanagementpage_handlemobilemenutoggle", "label": "handleMobileMenuToggle()", "file_type": "code", "source_file": "src\\pages\\learner\\SubscriptionManagementPage.tsx", "source_location": "L89"}, {"id": "subscriptionmanagementpage_showtoast", "label": "showToast()", "file_type": "code", "source_file": "src\\pages\\learner\\SubscriptionManagementPage.tsx", "source_location": "L90"}], "edges": [{"source": "subscriptionmanagementpage", "target": "react", "relation": "imports_from", "confidence": "EXTRACTED", "source_file": "src\\pages\\learner\\SubscriptionManagementPage.tsx", "source_location": "L1", "weight": 1.0}, {"source": "subscriptionmanagementpage", "target": "material", "relation": "imports_from", "confidence": "EXTRACTED", "source_file": "src\\pages\\learner\\SubscriptionManagementPage.tsx", "source_location": "L2", "weight": 1.0}, {"source": "subscriptionmanagementpage", "target": "icons_material", "relation": "imports_from", "confidence": "EXTRACTED", "source_file": "src\\pages\\learner\\SubscriptionManagementPage.tsx", "source_location": "L35", "weight": 1.0}, {"source": "subscriptionmanagementpage", "target": "react_query", "relation": "imports_from", "confidence": "EXTRACTED", "source_file": "src\\pages\\learner\\SubscriptionManagementPage.tsx", "source_location": "L59", "weight": 1.0}, {"source": "subscriptionmanagementpage", "target": "sidebar", "relation": "imports_from", "confidence": "EXTRACTED", "source_file": "src\\pages\\learner\\SubscriptionManagementPage.tsx", "source_location": "L60", "weight": 1.0}, {"source": "subscriptionmanagementpage", "target": "topbar", "relation": "imports_from", "confidence": "EXTRACTED", "source_file": "src\\pages\\learner\\SubscriptionManagementPage.tsx", "source_location": "L61", "weight": 1.0}, {"source": "subscriptionmanagementpage", "target": "react_router_dom", "relation": "imports_from", "confidence": "EXTRACTED", "source_file": "src\\pages\\learner\\SubscriptionManagementPage.tsx", "source_location": "L62", "weight": 1.0}, {"source": "subscriptionmanagementpage", "target": "uselearning", "relation": "imports_from", "confidence": "EXTRACTED", "source_file": "src\\pages\\learner\\SubscriptionManagementPage.tsx", "source_location": "L63", "weight": 1.0}, {"source": "subscriptionmanagementpage", "target": "usepayments", "relation": "imports_from", "confidence": "EXTRACTED", "source_file": "src\\pages\\learner\\SubscriptionManagementPage.tsx", "source_location": "L64", "weight": 1.0}, {"source": "subscriptionmanagementpage", "target": "payments_services", "relation": "imports_from", "confidence": "EXTRACTED", "source_file": "src\\pages\\learner\\SubscriptionManagementPage.tsx", "source_location": "L72", "weight": 1.0}, {"source": "subscriptionmanagementpage", "target": "livestream_services", "relation": "imports_from", "confidence": "EXTRACTED", "source_file": "src\\pages\\learner\\SubscriptionManagementPage.tsx", "source_location": "L73", "weight": 1.0}, {"source": "subscriptionmanagementpage", "target": "paymenterrors", "relation": "imports_from", "confidence": "EXTRACTED", "source_file": "src\\pages\\learner\\SubscriptionManagementPage.tsx", "source_location": "L74", "weight": 1.0}, {"source": "subscriptionmanagementpage", "target": "types", "relation": "imports_from", "confidence": "EXTRACTED", "source_file": "src\\pages\\learner\\SubscriptionManagementPage.tsx", "source_location": "L75", "weight": 1.0}, {"source": "subscriptionmanagementpage", "target": "types", "relation": "imports_from", "confidence": "EXTRACTED", "source_file": "src\\pages\\learner\\SubscriptionManagementPage.tsx", "source_location": "L76", "weight": 1.0}, {"source": "subscriptionmanagementpage", "target": "subscriptionmanagementpage_handlemobilemenutoggle", "relation": "contains", "confidence": "EXTRACTED", "source_file": "src\\pages\\learner\\SubscriptionManagementPage.tsx", "source_location": "L89", "weight": 1.0}, {"source": "subscriptionmanagementpage", "target": "subscriptionmanagementpage_showtoast", "relation": "contains", "confidence": "EXTRACTED", "source_file": "src\\pages\\learner\\SubscriptionManagementPage.tsx", "source_location": "L90", "weight": 1.0}]}