{"nodes": [{"id": "quizplayer", "label": "QuizPlayer.tsx", "file_type": "code", "source_file": "src\\components\\learner\\quiz-player\\QuizPlayer.tsx", "source_location": "L1"}, {"id": "quizplayer_usecountdown", "label": "useCountdown()", "file_type": "code", "source_file": "src\\components\\learner\\quiz-player\\QuizPlayer.tsx", "source_location": "L47"}, {"id": "quizplayer_gradequiz", "label": "gradeQuiz()", "file_type": "code", "source_file": "src\\components\\learner\\quiz-player\\QuizPlayer.tsx", "source_location": "L69"}], "edges": [{"source": "quizplayer", "target": "react", "relation": "imports_from", "confidence": "EXTRACTED", "source_file": "src\\components\\learner\\quiz-player\\QuizPlayer.tsx", "source_location": "L1", "weight": 1.0}, {"source": "quizplayer", "target": "material", "relation": "imports_from", "confidence": "EXTRACTED", "source_file": "src\\components\\learner\\quiz-player\\QuizPlayer.tsx", "source_location": "L2", "weight": 1.0}, {"source": "quizplayer", "target": "icons_material", "relation": "imports_from", "confidence": "EXTRACTED", "source_file": "src\\components\\learner\\quiz-player\\QuizPlayer.tsx", "source_location": "L7", "weight": 1.0}, {"source": "quizplayer", "target": "types", "relation": "imports_from", "confidence": "EXTRACTED", "source_file": "src\\components\\learner\\quiz-player\\QuizPlayer.tsx", "source_location": "L18", "weight": 1.0}, {"source": "quizplayer", "target": "learning_services", "relation": "imports_from", "confidence": "EXTRACTED", "source_file": "src\\components\\learner\\quiz-player\\QuizPlayer.tsx", "source_location": "L19", "weight": 1.0}, {"source": "quizplayer", "target": "catalogue_services", "relation": "imports_from", "confidence": "EXTRACTED", "source_file": "src\\components\\learner\\quiz-player\\QuizPlayer.tsx", "source_location": "L20", "weight": 1.0}, {"source": "quizplayer", "target": "quizplayer_usecountdown", "relation": "contains", "confidence": "EXTRACTED", "source_file": "src\\components\\learner\\quiz-player\\QuizPlayer.tsx", "source_location": "L47", "weight": 1.0}, {"source": "quizplayer", "target": "quizplayer_gradequiz", "relation": "contains", "confidence": "EXTRACTED", "source_file": "src\\components\\learner\\quiz-player\\QuizPlayer.tsx", "source_location": "L69", "weight": 1.0}]}