{"nodes": [{"id": "trustedbysection", "label": "TrustedBySection.tsx", "file_type": "code", "source_file": "src\\components\\business\\TrustedBySection.tsx", "source_location": "L1"}], "edges": [{"source": "trustedbysection", "target": "react", "relation": "imports_from", "confidence": "EXTRACTED", "source_file": "src\\components\\business\\TrustedBySection.tsx", "source_location": "L1", "weight": 1.0}, {"source": "trustedbysection", "target": "material", "relation": "imports_from", "confidence": "EXTRACTED", "source_file": "src\\components\\business\\TrustedBySection.tsx", "source_location": "L2", "weight": 1.0}]}